containerizeme/__init__.py
containerizeme/optimize.py
containerizeme/utils.py
tests/__init__.py
tests/test_optimize.py
ContainerizeMe-0.1.1.dist-info/LICENSE
ContainerizeMe-0.1.1.dist-info/METADATA
ContainerizeMe-0.1.1.dist-info/WHEEL
ContainerizeMe-0.1.1.dist-info/top_level.txt
ContainerizeMe-0.1.1.dist-info/RECORD
